soracom_api/__init__.py
soracom_api/api/__init__.py
soracom_api/api/audit_log_api.py
soracom_api/api/auth_api.py
soracom_api/api/billing_api.py
soracom_api/api/cell_location_api.py
soracom_api/api/credential_api.py
soracom_api/api/data_entry_api.py
soracom_api/api/device_api.py
soracom_api/api/device_object_model_api.py
soracom_api/api/diagnostic_api.py
soracom_api/api/email_api.py
soracom_api/api/event_handler_api.py
soracom_api/api/file_entry_api.py
soracom_api/api/files_api.py
soracom_api/api/gadget_api.py
soracom_api/api/group_api.py
soracom_api/api/lagoon_api.py
soracom_api/api/log_api.py
soracom_api/api/lora_device_api.py
soracom_api/api/lora_gateway_api.py
soracom_api/api/lora_network_set_api.py
soracom_api/api/operator_api.py
soracom_api/api/order_api.py
soracom_api/api/payment_api.py
soracom_api/api/port_mapping_api.py
soracom_api/api/query_api.py
soracom_api/api/role_api.py
soracom_api/api/shipping_address_api.py
soracom_api/api/sigfox_device_api.py
soracom_api/api/sim_api.py
soracom_api/api/soralet_api.py
soracom_api/api/stats_api.py
soracom_api/api/subscriber_api.py
soracom_api/api/system_notification_api.py
soracom_api/api/user_api.py
soracom_api/api/virtual_private_gateway_api.py
soracom_api/api_client.py
soracom_api/apis/__init__.py
soracom_api/configuration.py
soracom_api/exceptions.py
soracom_api/model/__init__.py
soracom_api/model/action_config.py
soracom_api/model/action_config_property.py
soracom_api/model/air_stats_response.py
soracom_api/model/api_audit_log_entry.py
soracom_api/model/api_call_error.py
soracom_api/model/api_call_error_message.py
soracom_api/model/arc_credential_attach_request.py
soracom_api/model/arc_credential_attach_response.py
soracom_api/model/arc_credential_renew_request.py
soracom_api/model/arc_credential_renew_response.py
soracom_api/model/arc_session_create_response.py
soracom_api/model/arc_session_status.py
soracom_api/model/attach_role_request.py
soracom_api/model/attribute_update.py
soracom_api-0.0.2.dist-info/WHEEL
soracom_api-0.0.2.dist-info/METADATA
soracom_api-0.0.2.dist-info/RECORD
